stylometer/__init__.py
stylometer/stylometer.py
stylometer-1.5.dist-info/METADATA
stylometer-1.5.dist-info/WHEEL
stylometer-1.5.dist-info/top_level.txt
stylometer-1.5.dist-info/RECORD
